{"19":{"VET/09":29,"VET/08":24,"VET/10":21,"VET/02":20,"VET/07":18,"VET/01":17,"VET/05":16,"BIO/10":16,"VET/06":15,"VET/03":14,"AGR/18":12,"MED/18":12,"AGR/01":12,"AGR/17":12,"BIO/01":10,"AGR/10":10,"AGR/19":10,"MED/41":10,"MED/21":10,"MED/19":10,"AGR/20":10,"MED/13":10,"MED/09":10,"MED/06":10,"BIO/11":10,"VET/04":10,"BIO/05":10,"AGR/07":8,"CHIM/11":8,"CHIM/12":8,"GEO/01":8,"GEO/02":8,"GEO/03":8,"GEO/04":8,"GEO/05":8,"GEO/06":8,"GEO/07":8,"GEO/08":8,"GEO/09":8,"GEO/10":8,"GEO/11":8,"GEO/12":8,"MAT/01":8,"BIO/02":8,"BIO/03":8,"BIO/04":8,"CHIM/09":8,"BIO/06":8,"BIO/07":8,"BIO/08":8,"BIO/09":8,"CHIM/08":8,"CHIM/07":8,"BIO/12":8,"BIO/13":8,"BIO/14":8,"BIO/15":8,"BIO/16":8,"BIO/17":8,"BIO/18":8,"BIO/19":8,"MED/01":8,"MED/02":8,"MED/03":8,"MED/04":8,"MED/05":8,"CHIM/06":8,"MED/07":8,"MED/08":8,"CHIM/05":8,"MED/10":8,"MED/11":8,"MED/12":8,"CHIM/04":8,"MED/14":8,"MED/15":8,"MED/16":8,"MED/17":8,"CHIM/03":8,"CHIM/02":8,"MED/20":8,"CHIM/01":8,"MED/22":8,"MED/23":8,"MED/24":8,"MED/25":8,"MED/26":8,"MED/27":8,"MED/28":8,"MED/29":8,"MED/30":8,"MED/31":8,"MED/32":8,"MED/33":8,"MED/34":8,"MED/35":8,"MED/36":8,"MED/37":8,"MED/38":8,"MED/39":8,"MED/40":8,"FIS/08":8,"MED/42":8,"MED/43":8,"MED/44":8,"MED/45":8,"MED/46":8,"MED/47":8,"MED/48":8,"MED/49":8,"MED/50":8,"FIS/07":8,"AGR/02":8,"AGR/03":8,"AGR/04":8,"AGR/05":8,"AGR/06":8,"CHIM/10":8,"AGR/08":8,"AGR/09":8,"FIS/06":8,"AGR/11":8,"AGR/12":8,"AGR/13":8,"AGR/14":8,"AGR/15":8,"AGR/16":8,"FIS/05":8,"FIS/04":8,"FIS/03":8,"FIS/02":8,"FIS/01":8,"INF/01":8,"MAT/09":8,"MAT/08":8,"MAT/07":8,"MAT/06":8,"MAT/05":8,"MAT/04":8,"MAT/03":8,"MAT/02":8,"L-ANT/01":8,"L-ANT/02":8,"L-ANT/03":8,"L-ANT/04":8,"L-ANT/05":8,"L-ANT/06":8,"L-ANT/07":8,"L-ANT/08":8,"L-ANT/09":8,"L-ANT/10":8,"L-ART/01":8,"L-ART/02":8,"L-ART/03":8,"L-ART/04":8,"L-ART/05":8},"20":{"VET/09":27,"VET/08":24,"VET/10":21,"VET/02":18,"BIO/10":16,"VET/01":15,"VET/07":15,"VET/05":14,"VET/06":14,"VET/03":13,"AGR/19":13,"AGR/18":12,"AGR/17":12,"BIO/01":10,"AGR/01":10,"MED/41":10,"MED/21":10,"MED/19":10,"MED/18":10,"BIO/12":10,"BIO/11":10,"AGR/10":10,"BIO/05":10,"AGR/07":8,"CHIM/07":8,"CHIM/08":8,"CHIM/09":8,"CHIM/10":8,"CHIM/11":8,"CHIM/12":8,"GEO/01":8,"GEO/02":8,"GEO/03":8,"GEO/04":8,"GEO/05":8,"GEO/06":8,"GEO/07":8,"GEO/08":8,"GEO/09":8,"GEO/10":8,"GEO/11":8,"GEO/12":8,"MAT/01":8,"BIO/02":8,"BIO/03":8,"BIO/04":8,"CHIM/05":8,"BIO/06":8,"BIO/07":8,"BIO/08":8,"BIO/09":8,"CHIM/04":8,"CHIM/03":8,"CHIM/02":8,"BIO/13":8,"BIO/14":8,"BIO/15":8,"BIO/16":8,"BIO/17":8,"BIO/18":8,"BIO/19":8,"MED/01":8,"MED/02":8,"MED/03":8,"MED/04":8,"MED/05":8,"MED/06":8,"MED/07":8,"MED/08":8,"MED/09":8,"MED/10":8,"MED/11":8,"MED/12":8,"MED/13":8,"MED/14":8,"MED/15":8,"MED/16":8,"MED/17":8,"CHIM/01":8,"FIS/08":8,"MED/20":8,"FIS/07":8,"MED/22":8,"MED/23":8,"MED/24":8,"MED/25":8,"MED/26":8,"MED/27":8,"MED/28":8,"MED/29":8,"MED/30":8,"MED/31":8,"MED/32":8,"MED/33":8,"MED/34":8,"MED/35":8,"MED/36":8,"MED/37":8,"MED/38":8,"MED/39":8,"MED/40":8,"FIS/06":8,"MED/42":8,"MED/43":8,"MED/44":8,"MED/45":8,"MED/46":8,"MED/47":8,"MED/48":8,"MED/49":8,"MED/50":8,"FIS/05":8,"AGR/02":8,"AGR/03":8,"AGR/04":8,"AGR/05":8,"AGR/06":8,"CHIM/06":8,"AGR/08":8,"AGR/09":8,"FIS/04":8,"AGR/11":8,"AGR/12":8,"AGR/13":8,"AGR/14":8,"AGR/15":8,"AGR/16":8,"FIS/03":8,"FIS/02":8,"FIS/01":8,"AGR/20":8,"INF/01":8,"MAT/09":8,"MAT/08":8,"VET/04":8,"MAT/07":8,"MAT/06":8,"MAT/05":8,"MAT/04":8,"MAT/03":8,"MAT/02":8,"L-ANT/01":8,"L-ANT/02":8,"L-ANT/03":8,"L-ANT/04":8,"L-ANT/05":8,"L-ANT/06":8,"L-ANT/07":8,"L-ANT/08":8,"L-ANT/09":8,"L-ANT/10":8,"L-ART/01":8,"L-ART/02":8,"L-ART/03":8,"L-ART/04":8,"L-ART/05":8},"21":{"VET/09":25,"VET/08":23,"VET/10":20,"VET/02":18,"VET/07":17,"VET/05":16,"VET/01":15,"VET/03":15,"VET/06":12,"BIO/12":12,"AGR/01":12,"BIO/10":12,"BIO/01":10,"AGR/17":10,"AGR/10":10,"AGR/18":10,"MED/41":10,"MED/18":10,"BIO/13":10,"VET/04":10,"BIO/11":10,"BIO/05":10,"AGR/19":9,"AGR/07":8,"CHIM/07":8,"CHIM/08":8,"CHIM/09":8,"CHIM/10":8,"CHIM/11":8,"CHIM/12":8,"GEO/01":8,"GEO/02":8,"GEO/03":8,"GEO/04":8,"GEO/05":8,"GEO/06":8,"GEO/07":8,"GEO/08":8,"GEO/09":8,"GEO/10":8,"GEO/11":8,"GEO/12":8,"MAT/01":8,"BIO/02":8,"BIO/03":8,"BIO/04":8,"CHIM/05":8,"BIO/06":8,"BIO/07":8,"BIO/08":8,"BIO/09":8,"CHIM/04":8,"CHIM/03":8,"CHIM/02":8,"CHIM/01":8,"BIO/14":8,"BIO/15":8,"BIO/16":8,"BIO/17":8,"BIO/18":8,"BIO/19":8,"MED/01":8,"MED/02":8,"MED/03":8,"MED/04":8,"MED/05":8,"MED/06":8,"MED/07":8,"MED/08":8,"MED/09":8,"MED/10":8,"MED/11":8,"MED/12":8,"MED/13":8,"MED/14":8,"MED/15":8,"MED/16":8,"MED/17":8,"FIS/08":8,"MED/19":8,"MED/20":8,"MED/21":8,"MED/22":8,"MED/23":8,"MED/24":8,"MED/25":8,"MED/26":8,"MED/27":8,"MED/28":8,"MED/29":8,"MED/30":8,"MED/31":8,"MED/32":8,"MED/33":8,"MED/34":8,"MED/35":8,"MED/36":8,"MED/37":8,"MED/38":8,"MED/39":8,"MED/40":8,"FIS/07":8,"MED/42":8,"MED/43":8,"MED/44":8,"MED/45":8,"MED/46":8,"MED/47":8,"MED/48":8,"MED/49":8,"MED/50":8,"FIS/06":8,"AGR/02":8,"AGR/03":8,"AGR/04":8,"AGR/05":8,"AGR/06":8,"CHIM/06":8,"AGR/08":8,"AGR/09":8,"FIS/05":8,"AGR/11":8,"AGR/12":8,"AGR/13":8,"AGR/14":8,"AGR/15":8,"AGR/16":8,"FIS/04":8,"FIS/03":8,"FIS/02":8,"AGR/20":8,"FIS/01":8,"INF/01":8,"MAT/09":8,"MAT/08":8,"MAT/07":8,"MAT/06":8,"MAT/05":8,"MAT/04":8,"MAT/03":8,"MAT/02":8,"L-ANT/01":8,"L-ANT/02":8,"L-ANT/03":8,"L-ANT/04":8,"L-ANT/05":8,"L-ANT/06":8,"L-ANT/07":8,"L-ANT/08":8,"L-ANT/09":8,"L-ANT/10":8,"L-ART/01":8,"L-ART/02":8,"L-ART/03":8,"L-ART/04":8,"L-ART/05":8},"22":{"VET/09":31,"VET/08":21,"VET/10":17,"VET/02":15,"VET/01":14,"VET/05":14,"VET/03":13,"VET/07":13,"MED/41":11,"MED/18":11,"VET/06":11,"MED/24":9,"BIO/10":9,"VET/04":8,"AGR/18":8,"MED/15":7,"BIO/12":7,"AGR/19":6,"BIO/07":5,"MED/42":5,"BIO/09":5,"BIO/11":5,"MED/30":5,"IUS/04":5,"CHIM/06":5,"CHIM/10":5,"BIO/06":5,"MED/13":4,"ING-IND/34":4,"BIO/14":4,"MED/17":4,"MED/14":3,"AGR/17":3,"AGR/01":2,"BIO/05":2,"BIO/01":2,"AGR/10":2,"MED/23":2,"MED/06":2,"MED/03":2,"BIO/13":2,"AGR/20":1},"23":{"VET/09":33,"VET/08":23,"VET/02":16,"VET/05":15,"VET/10":13,"VET/07":13,"VET/06":12,"VET/03":10,"MED/41":10,"VET/01":9,"BIO/06":8,"MED/18":8,"AGR/17":6,"MED/24":6,"MED/21":6,"MED/15":6,"GEO/01":4,"IUS/04":4,"ING-IND/34":4,"MED/13":4,"MED/42":4,"MED/17":4,"BIO/10":4,"MED/19":4,"BIO/14":4,"BIO/12":4,"MED/12":4,"AGR/18":3,"VET/04":3,"BIO/01":2,"MED/10":2,"BIO/05":2,"AGR/10":2,"BIO/11":2,"BIO/13":2,"MED/23":2,"AGR/01":2,"AGR/19":1,"AGR/20":1},"24":{"VET/09":33,"VET/08":19,"VET/02":15,"VET/07":15,"VET/10":15,"VET/01":14,"VET/03":12,"MED/41":10,"VET/05":10,"VET/06":9,"MED/18":8,"VET/04":7,"MED/24":6,"MED/21":6,"AGR/17":5,"MED/19":4,"MED/13":4,"BIO/12":4,"MED/17":4,"MED/12":4,"BIO/06":4,"ING-IND/34":4,"BIO/14":4,"BIO/10":4,"GEO/01":4,"AGR/18":4,"CHIM/10":3,"BIO/07":3,"BIO/09":3,"AGR/01":2,"AGR/10":2,"BIO/05":2,"MED/10":2,"BIO/13":2,"AGR/20":2,"BIO/03":2,"MED/15":2,"MED/23":2,"BIO/01":2,"AGR/19":1},"25":{"VET/09":32,"VET/08":19,"VET/10":15,"VET/06":15,"VET/07":14,"VET/02":14,"VET/05":13,"BIO/10":12,"VET/01":12,"VET/03":11,"AGR/18":11,"BIO/12":11,"MED/21":10,"MED/12":10,"MED/18":10,"AGR/17":9,"VET/04":9,"MED/42":9,"MED/41":8,"MED/24":7,"MED/10":7,"BIO/06":7,"MED/36":7,"MED/17":5,"MED/16":5,"MED/14":5,"MED/13":5,"MED/23":5,"MED/11":5,"MED/09":5,"BIO/09":5,"BIO/11":5,"MED/07":5,"BIO/13":5,"BIO/15":5,"BIO/16":5,"MED/46":5,"CHIM/08":5,"CHIM/09":5,"CHIM/10":5,"ING-IND/34":5,"MED/04":5,"MED/08":5,"MED/30":5,"MED/35":5,"BIO/14":5,"BIO/03":5,"MED/45":5,"MED/38":5,"CHIM/06":5,"AGR/19":4,"MED/15":4,"IUS/04":4,"INF/01":3,"MED/19":3,"AGR/07":2,"AGR/20":2,"BIO/05":2,"AGR/02":2,"AGR/03":2,"AGR/04":2,"AGR/01":2,"AGR/11":2,"AGR/12":2,"AGR/13":2,"AGR/15":2,"AGR/16":2,"BIO/04":2,"BIO/01":2,"MED/31":2,"MED/32":2,"SECS-P/13":2},"26":{"VET/09":34,"VET/08":24,"VET/07":22,"VET/05":21,"VET/06":21,"VET/01":20,"VET/03":20,"BIO/10":18,"VET/10":18,"VET/02":17,"VET/04":17,"AGR/18":14,"AGR/17":13,"BIO/09":12,"BIO/12":11,"BIO/06":11,"MED/42":9,"MED/07":9,"BIO/13":9,"BIO/14":9,"BIO/11":9,"MED/04":9,"CHIM/10":8,"BIO/05":8,"MED/41":7,"MED/18":7,"BIO/01":6,"MED/15":6,"BIO/03":6,"MED/45":5,"MED/46":5,"MED/09":5,"MED/10":5,"MED/11":5,"MED/12":5,"MED/13":5,"MED/14":5,"MED/16":5,"MED/17":5,"MED/38":5,"MED/21":5,"MED/23":5,"MED/24":5,"AGR/19":5,"MED/36":5,"BIO/16":5,"CHIM/06":5,"CHIM/08":5,"CHIM/09":5,"ING-IND/34":5,"MED/08":5,"MED/30":5,"MED/35":5,"BIO/15":5,"BIO/07":4,"BIO/08":4,"CHIM/01":4,"BIO/18":4,"IUS/04":4,"BIO/19":4,"INF/01":3,"AGR/20":3,"AGR/12":2,"AGR/02":2,"AGR/03":2,"AGR/04":2,"AGR/07":2,"AGR/11":2,"AGR/01":2,"AGR/13":2,"AGR/15":2,"AGR/16":2,"BIO/04":2,"MED/33":2,"SECS-P/13":2}}